pybbmini/__init__.py
pybbmini/base.py
pybbmini/bbmini.py
pybbmini/board.py
pybbmini/button.py
pybbmini/buzzer.py
pybbmini/display.py
pybbmini/mpu6050.py
pybbmini/pitch.py
pybbmini/symbol.py
pybbmini/touch.py
pybbmini-1.0.dist-info/METADATA
pybbmini-1.0.dist-info/WHEEL
pybbmini-1.0.dist-info/top_level.txt
pybbmini-1.0.dist-info/RECORD
