Metadata-Version: 2.1
Name: pybbmini
Version: 1.0
Summary: A Python Library For Bitblock-Mini
Home-page: https://github.com/devdio/bbmini-python.git
Author: devdio
Author-email: kei.devdio@gmail.com
License: UNKNOWN
Keywords: Bitblock32,bbmini,Bitblock,Bitblock-Mini
Platform: UNKNOWN
Classifier: Operating System :: Microsoft :: Windows
Classifier: Programming Language :: Python :: 3.8
Classifier: Programming Language :: Python :: 3.9
Classifier: Programming Language :: Python :: 3.10
Requires-Python: >=3.8
Requires-Dist: pyserial (==3.5)
